pygconsole/__init__.py
pygconsole/console.py
pygconsole/io.py
pygconsole/resources/fonts/DejaVu/AUTHORS
pygconsole/resources/fonts/DejaVu/DejaVuSansMono-Bold.ttf
pygconsole/resources/fonts/DejaVu/DejaVuSansMono-BoldOblique.ttf
pygconsole/resources/fonts/DejaVu/DejaVuSansMono-Oblique.ttf
pygconsole/resources/fonts/DejaVu/DejaVuSansMono.ttf
pygconsole/resources/fonts/DejaVu/LICENSE
pygconsole-0.2.0.dist-info/LICENSE.md
pygconsole-0.2.0.dist-info/METADATA
pygconsole-0.2.0.dist-info/WHEEL
pygconsole-0.2.0.dist-info/top_level.txt
pygconsole-0.2.0.dist-info/RECORD
