Metadata-Version: 2.1
Name: pygconsole
Version: 0.2.0
Summary: ANSI terminal emulation for Pygame
Home-page: https://github.com/devfred78/pygconsole
Author: devfred78
Author-email: devfred78@gmail.com
License: UNKNOWN
Project-URL: Bug Tracker, https://github.com/devfred78/pygconsole/issues
Project-URL: Sources, https://github.com/devfred78/pygconsole
Platform: UNKNOWN
Classifier: Development Status :: 3 - Alpha
Classifier: Intended Audience :: Developers
Classifier: Programming Language :: Python :: 3
Classifier: Programming Language :: Python :: 3.8
Classifier: Programming Language :: Python :: 3.9
Classifier: Programming Language :: Python :: 3.10
Classifier: License :: OSI Approved :: MIT License
Classifier: Operating System :: OS Independent
Classifier: Topic :: Software Development :: Libraries :: Python Modules
Classifier: Topic :: Terminals
Requires-Python: >=3.8
License-File: LICENSE.md
Requires-Dist: pygame (>=2.1.0)
Requires-Dist: colorlog (>=6.4.1)
Requires-Dist: numpy (>=1.6.2)
